Metadata-Version: 1.0
Name: fasta-manipulate-scripts
Version: 1.0.0
Summary: **What can this package do ?**
